cpf_tools/__init__.py
cpf_tools-1.5.1.dist-info/LICENSE.txt
cpf_tools-1.5.1.dist-info/METADATA
cpf_tools-1.5.1.dist-info/WHEEL
cpf_tools-1.5.1.dist-info/top_level.txt
cpf_tools-1.5.1.dist-info/RECORD
