Metadata-Version: 2.1
Name: cpf-tools
Version: 1.5.1
Summary: UNKNOWN
Home-page: https://github.com/BrunoASNascimento/cpf_tools
Author: Bruno Nascimento
Author-email: bruno-asn@outlook.com
License: MIT
Project-URL: Código fonte, https://github.com/BrunoASNascimento/cpf_tools
Project-URL: Download, https://github.com/BrunoASNascimento/cpf_tools/archive/master.zip
Keywords: format,cpf,validation
Platform: UNKNOWN
Classifier: Development Status :: 5 - Production/Stable
Classifier: Intended Audience :: Developers
Classifier: License :: OSI Approved :: MIT License
Classifier: Natural Language :: Portuguese (Brazilian)
Classifier: Operating System :: OS Independent
Classifier: Topic :: Software Development :: Internationalization
Requires-Python: >=3.6
License-File: LICENSE.txt
